seerbit/__init__.py
seerbit/client.py
seerbit/config.py
seerbit/enums.py
seerbit/exception.py
seerbit/httpclient.py
seerbit/seerbitlib.py
seerbit/utility.py
seerbit/validation.py
seerbit/interface/__init__.py
seerbit/interface/app_interface.py
seerbit/interface/service_interface.py
seerbit/service/__init__.py
seerbit/service/account_service.py
seerbit/service/authentication.py
seerbit/service/card_service.py
seerbit/service/mobile_money_service.py
seerbit/service/order_service.py
seerbit/service/recurring_service.py
seerbit/service/resource_service.py
seerbit/service/servicelib.py
seerbit/service/standard_checkout_service.py
seerbit/service/status_service.py
seerbit_python_v2-1.0.3.dist-info/LICENSE
seerbit_python_v2-1.0.3.dist-info/METADATA
seerbit_python_v2-1.0.3.dist-info/WHEEL
seerbit_python_v2-1.0.3.dist-info/top_level.txt
seerbit_python_v2-1.0.3.dist-info/RECORD
