Metadata-Version: 2.1
Name: seerbit-python-v2
Version: 1.0.3
Summary: A Seerbit API Library for Python
Home-page: https://github.com/seerbit/seerbit-python-api-library
Author: Seerbit
Author-email: developers@seerbit.com
License: UNKNOWN
Platform: UNKNOWN
Classifier: Programming Language :: Python :: 3
Requires-Python: >=3.7
